esp32_wifimanager-1.0.2.dist-info/licenses/LICENSE
wifiManager/__init__.py
wifiManager/manager.py
wifiManager/scanner.py
wifiManager/storage.py
wifiManager/version.py
esp32_wifimanager-1.0.2.dist-info/METADATA
esp32_wifimanager-1.0.2.dist-info/WHEEL
esp32_wifimanager-1.0.2.dist-info/top_level.txt
esp32_wifimanager-1.0.2.dist-info/RECORD
