Metadata-Version: 2.4
Name: esp32-wifimanager
Version: 1.0.2
Summary: WiFi Manager for ESP32 running MicroPython
Author: Ibrahim Salih
License: MIT
Keywords: micropython,esp32,wifi,iot
Classifier: Programming Language :: Python :: 3
Classifier: License :: OSI Approved :: MIT License
Classifier: Operating System :: OS Independent
License-File: LICENSE
Dynamic: license-file
